{
  "openapi": "3.1.0",
  "info": {
    "version": "1.0.0",
    "title": "My Zuplo API"
  },
  "paths": {
    "/order/all-filters": {
      "x-zuplo-path": {
        "pathMode": "open-api"
      },
      "get": {
        "summary": "Order: All filters",
        "description": "Lorem ipsum dolor sit amet, **consectetur adipiscing** elit, sed do `eiusmod tempor` incididunt ut labore et dolore magna aliqua.",
        "x-zuplo-route": {
          "corsPolicy": "anything-goes",
          "handler": {
            "export": "default",
            "module": "$import(./modules/order--all-filters)",
            "options": {}
          },
          "policies": {
            "inbound": []
          }
        },
        "operationId": "51cc7338-9f20-4a80-bfde-da8a90aafa49"
      }
    },
    "/type-ahead/:fieldName": {
      "x-zuplo-path": {
        "pathMode": "open-api"
      },
      "post": {
        "summary": "Type-Ahead Options",
        "description": "Lorem ipsum dolor sit amet, **consectetur adipiscing** elit, sed do `eiusmod tempor` incididunt ut labore et dolore magna aliqua.",
        "x-zuplo-route": {
          "corsPolicy": "none",
          "handler": {
            "export": "default",
            "module": "$import(./modules/order--all-filters)",
            "options": {}
          },
          "policies": {
            "inbound": []
          }
        },
        "operationId": "6c26b908-7f6d-4874-be04-c1c4f12c7bda"
      }
    }
  }
}